gajula.py
gajula-0.0.20.dist-info/LICENSE
gajula-0.0.20.dist-info/METADATA
gajula-0.0.20.dist-info/WHEEL
gajula-0.0.20.dist-info/top_level.txt
gajula-0.0.20.dist-info/RECORD
