Metadata-Version: 2.1
Name: gajula
Version: 0.0.20
Summary: Gajula Package consists of useful utilites and functions
Author: Jagadeesh Gajula
Classifier: Programming Language :: Python :: 3
Classifier: License :: OSI Approved :: MIT License
Classifier: Operating System :: OS Independent
Requires-Python: >=3.6
License-File: LICENSE
Requires-Dist: pytz
